pyavd_utils/LICENSE
pyavd_utils/__init__.py
pyavd_utils/passwords.pyd
pyavd_utils/passwords.pyi
pyavd_utils/py.typed
pyavd_utils/validation.pyd
pyavd_utils/validation.pyi
pyavd_utils-0.0.1.dist-info/licenses/pyavd_utils/LICENSE
pyavd_utils-0.0.1.dist-info/METADATA
pyavd_utils-0.0.1.dist-info/WHEEL
pyavd_utils-0.0.1.dist-info/top_level.txt
pyavd_utils-0.0.1.dist-info/RECORD
