Metadata-Version: 2.4
Name: pyavd-utils
Version: 0.0.1
Summary: Rust based utilities used by PyAVD. Should not be used directly and may not follow semantic versioning.
Author-email: Arista Networks <avd-dev@arista.com>
License-Expression: Apache-2.0
Project-URL: homepage, https://avd.arista.com
Project-URL: repository, https://github.com/aristanetworks/avd
Keywords: pyavd,pyavd-utils
Classifier: Development Status :: 3 - Alpha
Classifier: Intended Audience :: Developers
Classifier: Natural Language :: English
Classifier: Operating System :: OS Independent
Classifier: Programming Language :: Python
Classifier: Programming Language :: Python :: 3.10
Classifier: Programming Language :: Python :: 3.11
Classifier: Programming Language :: Python :: 3.12
Classifier: Programming Language :: Python :: 3.13
Classifier: Programming Language :: Python :: 3.14
Classifier: Programming Language :: Rust
Classifier: Topic :: Software Development :: Libraries :: Python Modules
Classifier: Topic :: Utilities
Requires-Python: >=3.10
License-File: pyavd_utils/LICENSE
Dynamic: license-file
